odoo/addons/partner_group/README.rst
odoo/addons/partner_group/__init__.py
odoo/addons/partner_group/__manifest__.py
odoo/addons/partner_group/i18n/es.po
odoo/addons/partner_group/i18n/partner_group.pot
odoo/addons/partner_group/i18n/pt.po
odoo/addons/partner_group/models/__init__.py
odoo/addons/partner_group/models/res_partner.py
odoo/addons/partner_group/readme/CONTRIBUTORS.rst
odoo/addons/partner_group/readme/DESCRIPTION.rst
odoo/addons/partner_group/readme/USAGE.rst
odoo/addons/partner_group/static/description/icon.png
odoo/addons/partner_group/static/description/index.html
odoo/addons/partner_group/views/res_partner_views.xml
odoo12_addon_partner_group-12.0.1.0.1.dist-info/METADATA
odoo12_addon_partner_group-12.0.1.0.1.dist-info/WHEEL
odoo12_addon_partner_group-12.0.1.0.1.dist-info/top_level.txt
odoo12_addon_partner_group-12.0.1.0.1.dist-info/RECORD
